camb_sdk-1.0.3.dist-info/licenses/LICENSE
cambai/__init__.py
cambai/api_client.py
cambai/api_response.py
cambai/configuration.py
cambai/exceptions.py
cambai/py.typed
cambai/rest.py
cambai/api/__init__.py
cambai/api/apis_api.py
cambai/api/audio_separation_api.py
cambai/api/dictionaries_api.py
cambai/api/dub_api.py
cambai/api/stories_api.py
cambai/api/text_to_audio_api.py
cambai/api/text_to_speech_api.py
cambai/api/text_to_voice_api.py
cambai/models/__init__.py
cambai/models/audio_output_file_url_response.py
cambai/models/audio_output_type.py
cambai/models/audio_separation_run_info_response.py
cambai/models/body_translate_translate_post.py
cambai/models/create_api_key_request_payload.py
cambai/models/create_custom_voice_out.py
cambai/models/create_text_to_audio_request_payload.py
cambai/models/create_text_to_voice_request_payload.py
cambai/models/create_translated_story_request_payload.py
cambai/models/create_translated_tts_request_payload.py
cambai/models/create_translation_stream_request_payload.py
cambai/models/create_tts_request_payload.py
cambai/models/create_tts_stream_request_payload.py
cambai/models/dialogue_item.py
cambai/models/dictionary.py
cambai/models/dub_alt_format_response_body.py
cambai/models/dubbed_output_in_alt_format_request_payload.py
cambai/models/end_to_end_dubbing_request_payload.py
cambai/models/expire_api_key_request_payload.py
cambai/models/formalities.py
cambai/models/gender.py
cambai/models/http_validation_error.py
cambai/models/language_item.py
cambai/models/languages.py
cambai/models/orchestrator_pipeline_result.py
cambai/models/output_api_key.py
cambai/models/output_format.py
cambai/models/output_type.py
cambai/models/request_dubbed_output_in_alt_format200_response.py
cambai/models/run_info_response.py
cambai/models/story_run_info_response.py
cambai/models/task_id.py
cambai/models/task_status.py
cambai/models/text_to_voice_run_info_response.py
cambai/models/transcript_data_type.py
cambai/models/transcript_file_format.py
cambai/models/translation_result.py
camb_sdk-1.0.3.dist-info/METADATA
camb_sdk-1.0.3.dist-info/WHEEL
camb_sdk-1.0.3.dist-info/top_level.txt
camb_sdk-1.0.3.dist-info/RECORD
