Metadata-Version: 2.4
Name: camb-sdk
Version: 1.0.3
Summary: Camb AI Python SDK for Text-to-Speech, Voice Generation, and Audio APIs
Author-email: Camb AI <support@camb.ai>
License: MIT
Project-URL: Repository, https://github.com/Camb-ai/cambai-python-sdk
Project-URL: Documentation, https://docs.camb.ai
Keywords: AI,Dubbing,Text-to-Speech,Voice,Audio,SDK
Requires-Python: >=3.9
License-File: LICENSE
Requires-Dist: urllib3<3.0.0,>=2.1.0
Requires-Dist: python-dateutil>=2.8.2
Requires-Dist: pydantic>=2
Requires-Dist: typing-extensions>=4.7.1
Dynamic: license-file
